{"objectName":"bcellEnumerationTestOrder","tableName":"tblBCellEnumerationTestOrder","fields":[{"isPrimaryKey":false,"name":"method","width":"50","dataType":"string","defaultValue":"null","isNullable":"True","sqlName":"Method"},{"isPrimaryKey":false,"name":"asrComment","width":"1000","dataType":"string","defaultValue":"null","isNullable":"True","sqlName":"ASRComment"},{"isPrimaryKey":false,"name":"wbc","width":"","dataType":"string","defaultValue":"null","isNullable":"True","sqlName":"WBC"},{"isPrimaryKey":false,"name":"lymphocytePercentage","width":"","dataType":"string","defaultValue":"null","isNullable":"True","sqlName":"LymphocytePercentage"},{"isPrimaryKey":false,"name":"cd19BCellPositivePercent","width":"","dataType":"string","defaultValue":"null","isNullable":"True","sqlName":"CD19BCellPositivePercent"},{"isPrimaryKey":false,"name":"cd20BCellPositivePercent","width":"","dataType":"string","defaultValue":"null","isNullable":"True","sqlName":"CD20BCellPositivePercent"},{"isPrimaryKey":false,"name":"cd19AbsoluteCount","width":"","dataType":"string","defaultValue":"null","isNullable":"True","sqlName":"CD19AbsoluteCount"},{"isPrimaryKey":false,"name":"cd20AbsoluteCount","width":"","dataType":"string","defaultValue":"null","isNullable":"True","sqlName":"CD20AbsoluteCount"}]}
