{"objectName":"panelSetOrderCPTCode","tableName":"tblPanelSetOrderCPTCode","fields":[{"isPrimaryKey":false,"name":"objectId","width":"50","dataType":"string","defaultValue":"null","isNullable":"True","sqlName":"ObjectId"},{"isPrimaryKey":true,"name":"panelSetOrderCPTCodeId","width":"50","dataType":"string","defaultValue":"null","isNullable":"False","sqlName":"PanelSetOrderCPTCodeId"},{"isPrimaryKey":false,"name":"referenceId","width":"50","dataType":"string","defaultValue":"null","isNullable":"True","sqlName":"ReferenceId"},{"isPrimaryKey":false,"name":"reportNo","width":"20","dataType":"string","defaultValue":"null","isNullable":"True","sqlName":"ReportNo"},{"isPrimaryKey":false,"name":"clientId","width":"11","dataType":"number","defaultValue":"null","isNullable":"True","sqlName":"ClientId"},{"isPrimaryKey":false,"name":"quantity","width":"11","dataType":"number","defaultValue":"null","isNullable":"False","sqlName":"Quantity"},{"isPrimaryKey":false,"name":"cptCode","width":"50","dataType":"string","defaultValue":"null","isNullable":"True","sqlName":"CPTCode"},{"isPrimaryKey":false,"name":"modifier","width":"50","dataType":"string","defaultValue":"null","isNullable":"True","sqlName":"Modifier"},{"isPrimaryKey":false,"name":"codeableDescription","width":"1000","dataType":"string","defaultValue":"null","isNullable":"True","sqlName":"CodeableDescription"},{"isPrimaryKey":false,"name":"codeableType","width":"50","dataType":"string","defaultValue":"null","isNullable":"True","sqlName":"CodeableType"},{"isPrimaryKey":false,"name":"entryType","width":"50","dataType":"string","defaultValue":"null","isNullable":"False","sqlName":"EntryType"},{"isPrimaryKey":false,"name":"specimenOrderId","width":"50","dataType":"string","defaultValue":"null","isNullable":"True","sqlName":"SpecimenOrderId"},{"isPrimaryKey":false,"name":"postDate","width":"3","dataType":"string","defaultValue":"null","isNullable":"True","sqlName":"PostDate"},{"isPrimaryKey":false,"name":"codeType","width":"50","dataType":"string","defaultValue":"null","isNullable":"True","sqlName":"CodeType"}]}
